quantum_data_embedding_suite/__init__.py
quantum_data_embedding_suite/cli.py
quantum_data_embedding_suite/licensing.py
quantum_data_embedding_suite/metrics.py
quantum_data_embedding_suite/pipeline.py
quantum_data_embedding_suite/utils.py
quantum_data_embedding_suite/visualization.py
quantum_data_embedding_suite/__pycache__/__init__.cpython-313.opt-2.pyc
quantum_data_embedding_suite/__pycache__/__init__.cpython-313.pyc
quantum_data_embedding_suite/__pycache__/cli.cpython-313.opt-2.pyc
quantum_data_embedding_suite/__pycache__/cli.cpython-313.pyc
quantum_data_embedding_suite/__pycache__/licensing.cpython-313.opt-2.pyc
quantum_data_embedding_suite/__pycache__/licensing.cpython-313.pyc
quantum_data_embedding_suite/__pycache__/metrics.cpython-313.opt-2.pyc
quantum_data_embedding_suite/__pycache__/metrics.cpython-313.pyc
quantum_data_embedding_suite/__pycache__/pipeline.cpython-313.opt-2.pyc
quantum_data_embedding_suite/__pycache__/pipeline.cpython-313.pyc
quantum_data_embedding_suite/__pycache__/utils.cpython-313.opt-2.pyc
quantum_data_embedding_suite/__pycache__/utils.cpython-313.pyc
quantum_data_embedding_suite/__pycache__/visualization.cpython-313.opt-2.pyc
quantum_data_embedding_suite/__pycache__/visualization.cpython-313.pyc
quantum_data_embedding_suite/backends/__init__.py
quantum_data_embedding_suite/backends/base.py
quantum_data_embedding_suite/backends/pennylane_backend.py
quantum_data_embedding_suite/backends/qiskit_backend.py
quantum_data_embedding_suite/backends/__pycache__/__init__.cpython-313.opt-2.pyc
quantum_data_embedding_suite/backends/__pycache__/__init__.cpython-313.pyc
quantum_data_embedding_suite/backends/__pycache__/base.cpython-313.opt-2.pyc
quantum_data_embedding_suite/backends/__pycache__/base.cpython-313.pyc
quantum_data_embedding_suite/backends/__pycache__/pennylane_backend.cpython-313.opt-2.pyc
quantum_data_embedding_suite/backends/__pycache__/pennylane_backend.cpython-313.pyc
quantum_data_embedding_suite-1.0.1.dist-info/licenses/LICENSE
quantum_data_embedding_suite-1.0.1.dist-info/licenses/license_info.py
quantum_data_embedding_suite-1.0.1.dist-info/METADATA
quantum_data_embedding_suite-1.0.1.dist-info/WHEEL
quantum_data_embedding_suite-1.0.1.dist-info/entry_points.txt
quantum_data_embedding_suite-1.0.1.dist-info/top_level.txt
quantum_data_embedding_suite-1.0.1.dist-info/RECORD
