Metadata-Version: 2.4
Name: quantum-data-embedding-suite
Version: 1.0.1
Summary: Advanced classical-to-quantum data embedding techniques for quantum machine learning
Home-page: https://github.com/krish567366/quantum-data-embedding-suite
Author: Krishna Bajpai
Author-email: Krishna Bajpai <bajpaikrishna715@gmail.com>
License: MIT
Project-URL: Homepage, https://github.com/krish567366/quantum-data-embedding-suite
Project-URL: Documentation, https://krish567366.github.io/quantum-data-embedding-suite
Project-URL: Repository, https://github.com/krish567366/quantum-data-embedding-suite
Project-URL: Issues, https://github.com/krish567366/quantum-data-embedding-suite/issues
Keywords: quantum,machine learning,embedding,qml,quantum computing
Classifier: Development Status :: 4 - Beta
Classifier: Intended Audience :: Science/Research
Classifier: License :: Other/Proprietary License
Classifier: Programming Language :: Python :: 3
Classifier: Programming Language :: Python :: 3.8
Classifier: Programming Language :: Python :: 3.9
Classifier: Programming Language :: Python :: 3.10
Classifier: Programming Language :: Python :: 3.11
Classifier: Topic :: Scientific/Engineering :: Physics
Classifier: Topic :: Scientific/Engineering :: Artificial Intelligence
Requires-Python: >=3.8
License-File: LICENSE
License-File: license_info.py
Requires-Dist: qiskit>=0.45.0
Requires-Dist: pennylane>=0.32.0
Requires-Dist: numpy>=1.21.0
Requires-Dist: scipy>=1.7.0
Requires-Dist: scikit-learn>=1.0.0
Requires-Dist: matplotlib>=3.5.0
Requires-Dist: seaborn>=0.11.0
Requires-Dist: pandas>=1.3.0
Requires-Dist: tqdm>=4.62.0
Requires-Dist: pyyaml>=6.0
Requires-Dist: click>=8.0.0
Requires-Dist: jupyter>=1.0.0
Requires-Dist: ipywidgets>=7.6.0
Requires-Dist: plotly>=5.0.0
Requires-Dist: scikit-optimize>=0.9.0
Requires-Dist: quantummeta-license>=1.0.0
Provides-Extra: dev
Requires-Dist: pytest>=6.0; extra == "dev"
Requires-Dist: pytest-cov>=3.0; extra == "dev"
Requires-Dist: black>=22.0; extra == "dev"
Requires-Dist: flake8>=4.0; extra == "dev"
Requires-Dist: mypy>=0.950; extra == "dev"
Requires-Dist: pre-commit>=2.15; extra == "dev"
Provides-Extra: docs
Requires-Dist: mkdocs>=1.4.0; extra == "docs"
Requires-Dist: mkdocs-material>=8.5.0; extra == "docs"
Requires-Dist: mkdocstrings[python]>=0.19.0; extra == "docs"
Requires-Dist: mkdocs-jupyter>=0.21.0; extra == "docs"
Requires-Dist: mkdocs-gallery>=0.7.0; extra == "docs"
Provides-Extra: aws
Requires-Dist: amazon-braket-sdk>=1.50.0; extra == "aws"
Provides-Extra: ibm
Requires-Dist: qiskit-ibm-runtime>=0.15.0; extra == "ibm"
Provides-Extra: ionq
Requires-Dist: cirq-ionq>=1.0.0; extra == "ionq"
Dynamic: author
Dynamic: home-page
Dynamic: license-file
Dynamic: requires-python
